power_spherical/__init__.py
power_spherical/distributions.py
power_spherical-0.8.1.dist-info/LICENSE
power_spherical-0.8.1.dist-info/LICENSES/CC0-1.0.txt
power_spherical-0.8.1.dist-info/LICENSES/MIT.txt
power_spherical-0.8.1.dist-info/METADATA
power_spherical-0.8.1.dist-info/WHEEL
power_spherical-0.8.1.dist-info/RECORD
