Metadata-Version: 2.1
Name: power-spherical
Version: 0.8.1
Summary: Pytorch implementation of the Power Spherical distribution
Home-page: https://github.com/andife/power_spherical
License: MIT
Keywords: pytorch,machine-learning,deep-learning,manifold-learning
Author: Nicola De Cao
Maintainer: Andreas Fehlner
Maintainer-email: fehlner@arcor.de
Requires-Python: >=3.9,<4.0
Classifier: Development Status :: 5 - Production/Stable
Classifier: License :: OSI Approved :: MIT License
Classifier: Operating System :: OS Independent
Classifier: Programming Language :: Python :: 3
Classifier: Programming Language :: Python :: 3.9
Classifier: Programming Language :: Python :: 3.10
Classifier: Programming Language :: Python :: 3.11
Classifier: Programming Language :: Python :: 3.12
Project-URL: Repository, https://github.com/andife/power_spherical
